tryagain.py
tryagain-1.0.dist-info/DESCRIPTION.rst
tryagain-1.0.dist-info/METADATA
tryagain-1.0.dist-info/RECORD
tryagain-1.0.dist-info/WHEEL
tryagain-1.0.dist-info/metadata.json
tryagain-1.0.dist-info/top_level.txt
