Metadata-Version: 2.0
Name: tryagain
Version: 1.0
Summary: A lightweight and pythonic retry helper
Home-page: https://github.com/tfeldmann/tryagain
Author: Thomas Feldmann
Author-email: mail@tfeldmann.de
License: MIT
Keywords: retry,unstable,tryagain,redo,try,again,exception
Platform: UNKNOWN
Classifier: Development Status :: 5 - Production/Stable
Classifier: Intended Audience :: Developers
Classifier: License :: OSI Approved :: MIT License
Classifier: Programming Language :: Python :: 2
Classifier: Programming Language :: Python :: 2.6
Classifier: Programming Language :: Python :: 2.7
Classifier: Programming Language :: Python :: 3
Classifier: Programming Language :: Python :: 3.2
Classifier: Programming Language :: Python :: 3.3
Classifier: Programming Language :: Python :: 3.4
Classifier: Programming Language :: Python :: 3.5
